link_checker.py
markdown_link_checker-0.1.0.dist-info/LICENSE.txt
markdown_link_checker-0.1.0.dist-info/METADATA
markdown_link_checker-0.1.0.dist-info/WHEEL
markdown_link_checker-0.1.0.dist-info/entry_points.txt
markdown_link_checker-0.1.0.dist-info/top_level.txt
markdown_link_checker-0.1.0.dist-info/RECORD
