Metadata-Version: 2.1
Name: markdown-link-checker
Version: 0.1.0
Summary: A command-line interface that, given a markdown file, verifies all the links work.
Home-page: https://github.com/tecladocode/markdown-link-checker
Author: Jose Salvatierra
License: UNKNOWN
Platform: UNKNOWN
Classifier: Programming Language :: Python :: 3
Classifier: License :: OSI Approved :: MIT License
Classifier: Operating System :: OS Independent
Requires-Python: >=3.8
License-File: LICENSE.txt
Requires-Dist: Click
Requires-Dist: markdown
Requires-Dist: beautifulsoup4
Requires-Dist: requests
Requires-Dist: rich
